design.sv
module mux4to1_case (
    input  wire [1:0] sel,
    input  wire [3:0] in,
    output reg        out
);
    always @(*) begin
        case (sel)
            2'b00: out = in[0];
            2'b01: out = in[1];
            2'b10: out = in[2];
            2'b11: out = in[3];
        endcase
    end
endmodule

testbench.sv

module tb_mux4to1;

    reg [1:0] sel;
    reg [3:0] in;

    wire out_assign;
    wire out_case;
    wire out_if;

    
    mux4to1_case mux_case (
        .sel(sel),
        .in(in),
        .out(out_case)
    );

    

    initial begin
      $dumpfile("mux4to1_case.vcd");
      $dumpvars;
        $display("Time\tSel\tIn\tAssign\tCase\tIf");
        $monitor("%0t\t%02b\t%b\t%b\t%b\t%b", 
                  $time, sel, in, out_case);

        in = 4'b1010; 

        sel = 2'b00; #10;
        sel = 2'b01; #10;
        sel = 2'b10; #10;
        sel = 2'b11; #10;

        in = 4'b0101;  
        sel = 2'b00; #10;
        sel = 2'b01; #10;
        sel = 2'b10; #10;
        sel = 2'b11; #10;

        $finish;
    end

endmodule

mux4to1_case.vcd
$date
	Thu Aug  7 09:22:53 2025
$end
$version
	Icarus Verilog
$end
$timescale
	1s
$end
$scope module tb_mux4to1 $end
$var wire 1 ! out_case $end
$var reg 4 " in [3:0] $end
$var reg 2 # sel [1:0] $end
$scope module mux_case $end
$var wire 4 $ in [3:0] $end
$var wire 2 % sel [1:0] $end
$var reg 1 ! out $end
$upscope $end
$upscope $end
$enddefinitions $end
$comment Show the parameter values. $end
$dumpall
$end
#0
$dumpvars
b0 %
b1010 $
b0 #
b1010 "
0!
$end
#10
1!
b1 #
b1 %
#20
0!
b10 #
b10 %
#30
1!
b11 #
b11 %
#40
b0 #
b0 %
b101 "
b101 $
#50
0!
b1 #
b1 %
#60
1!
b10 #
b10 %
#70
0!
b11 #
b11 %
